llama_index/agent/dashscope/__init__.py
llama_index/agent/dashscope/base.py
llama_index_agent_dashscope-0.3.1.dist-info/METADATA
llama_index_agent_dashscope-0.3.1.dist-info/WHEEL
llama_index_agent_dashscope-0.3.1.dist-info/licenses/LICENSE
llama_index_agent_dashscope-0.3.1.dist-info/RECORD
