Metadata-Version: 2.4
Name: llama-index-agent-dashscope
Version: 0.3.1
Summary: llama-index agent dashscope integration
Author-email: Tianbing Ye <tianbing.ytb@alibaba-inc.com>
License-Expression: MIT
License-File: LICENSE
Requires-Python: <4.0,>=3.9
Requires-Dist: dashscope>=1.17.0
Requires-Dist: llama-index-core<0.13,>=0.12.0
